rpathtool
